finwise/__init__.py
finwise/_client.py
finwise/_config.py
finwise/_http.py
finwise/_version.py
finwise/exceptions.py
finwise/models/__init__.py
finwise/models/account.py
finwise/models/account_balance.py
finwise/models/transaction.py
finwise/models/transaction_category.py
finwise/resources/__init__.py
finwise/resources/_base.py
finwise/resources/account_balances.py
finwise/resources/accounts.py
finwise/resources/transaction_categories.py
finwise/resources/transactions.py
finwise/types/__init__.py
finwise/types/pagination.py
finwise_python-1.4.0.dist-info/METADATA
finwise_python-1.4.0.dist-info/WHEEL
finwise_python-1.4.0.dist-info/licenses/LICENSE
finwise_python-1.4.0.dist-info/RECORD
